newsegmentation/__init__.py
newsegmentation/_algorithms.py
newsegmentation/_architecture.py
newsegmentation/_databasetrans.py
newsegmentation/_dserial.py
newsegmentation/_gtreader.py
newsegmentation/_slm.py
newsegmentation/_structures.py
newsegmentation/_tdm.py
newsegmentation-1.5.1.dist-info/LICENSE
newsegmentation-1.5.1.dist-info/METADATA
newsegmentation-1.5.1.dist-info/WHEEL
newsegmentation-1.5.1.dist-info/top_level.txt
newsegmentation-1.5.1.dist-info/RECORD
