Metadata-Version: 2.1
Name: newsegmentation
Version: 1.5.1
Summary: Package for news segmentation architecture.
Home-page: https://github.com/iTzAlver/newsegmentation
Author: Alberto Palomo Alonso
Author-email: a.palomo@uah.es
Project-URL: Documentation, https://github.com/iTzAlver/newsegmentation/blob/master/README.md
Project-URL: Bug Reports, https://github.com/iTzAlver/newsegmentation/issues
Project-URL: Source Code, https://github.com/iTzAlver/newsegmentation.git
Keywords: deeplearning,ml,api
Classifier: Development Status :: 5 - Production/Stable
Classifier: Intended Audience :: Science/Research
Classifier: Topic :: Software Development :: Build Tools
Classifier: Programming Language :: Python :: 3
Classifier: License :: OSI Approved :: MIT License
Classifier: Operating System :: OS Independent
Classifier: Topic :: Text Editors :: Text Processing
Classifier: Topic :: Text Processing
Classifier: Topic :: Text Processing :: Linguistic
Classifier: Topic :: Scientific/Engineering :: Artificial Intelligence
Requires-Python: >=3.8
License-File: LICENSE
Requires-Dist: matplotlib (>=3.5.0)
Requires-Dist: numpy (>=1.22.3)
Requires-Dist: torch (>=1.9.0)
Requires-Dist: nltk (>=3.6.5)
Requires-Dist: sklearn (>=0.0)
Requires-Dist: sentence-transformers (>=2.2.0)
Requires-Dist: googletrans (==4.0.0rc1)
Provides-Extra: dev
Requires-Dist: check-manifest ; extra == 'dev'
